monaco/__init__.py
monaco/case_runners.py
monaco/dvars_sensitivity.py
monaco/gaussian_statistics.py
monaco/globals.py
monaco/helper_functions.py
monaco/integration_statistics.py
monaco/mc_case.py
monaco/mc_enums.py
monaco/mc_multi_plot.py
monaco/mc_plot.py
monaco/mc_sampling.py
monaco/mc_sim.py
monaco/mc_val.py
monaco/mc_var.py
monaco/mc_varstat.py
monaco/order_statistics.py
monaco-0.20.1.dist-info/WHEEL
monaco-0.20.1.dist-info/METADATA
monaco-0.20.1.dist-info/RECORD
