Metadata-Version: 2.4
Name: monaco
Version: 0.20.1
Summary: Quantify uncertainty and sensitivities in your models with an industry-grade Monte Carlo library.
Author: Scott Shambaugh
Author-email: Scott Shambaugh <scott@theshamblog.com>
License-Expression: MIT
Classifier: Development Status :: 3 - Alpha
Classifier: Intended Audience :: Developers
Classifier: Intended Audience :: Science/Research
Classifier: Operating System :: OS Independent
Classifier: Topic :: Scientific/Engineering
Classifier: Topic :: Software Development
Classifier: Programming Language :: Python :: 3
Classifier: Programming Language :: Python :: 3 :: Only
Classifier: Programming Language :: Python :: 3.10
Classifier: Programming Language :: Python :: 3.11
Classifier: Programming Language :: Python :: 3.12
Classifier: Programming Language :: Python :: 3.13
Classifier: Programming Language :: Python :: 3.14
Requires-Dist: numpy>=1.26
Requires-Dist: scipy~=1.11
Requires-Dist: matplotlib~=3.6
Requires-Dist: tqdm~=4.0
Requires-Dist: psutil~=5.0
Requires-Dist: cloudpickle>=3.0
Requires-Dist: pillow>=10.3.0
Requires-Dist: typing-extensions>=4.15
Requires-Dist: distributed>=2024 ; extra == 'distributed'
Requires-Dist: numba>0.61 ; python_full_version < '3.14' and extra == 'numba'
Requires-Dist: pandas>=2.2 ; extra == 'pandas'
Requires-Python: >=3.10.0, <3.15
Project-URL: Repository, https://github.com/scottshambaugh/monaco/
Provides-Extra: distributed
Provides-Extra: numba
Provides-Extra: pandas
